nti/__init__.py
nti/externalization/__base_interfaces.cpython-313t-x86_64-linux-gnu.so
nti/externalization/__base_interfaces.pxd
nti/externalization/__init__.py
nti/externalization/__interface_cache.cpython-313t-x86_64-linux-gnu.so
nti/externalization/__interface_cache.pxd
nti/externalization/_base_interfaces.c
nti/externalization/_base_interfaces.py
nti/externalization/_compat.py
nti/externalization/_datastructures.cpython-313t-x86_64-linux-gnu.so
nti/externalization/_datastructures.pxd
nti/externalization/_interface_cache.c
nti/externalization/_interface_cache.py
nti/externalization/_singleton.cpython-313t-x86_64-linux-gnu.so
nti/externalization/_singleton.pxd
nti/externalization/_threadlocal.py
nti/externalization/autopackage.py
nti/externalization/configure.zcml
nti/externalization/datastructures.c
nti/externalization/datastructures.py
nti/externalization/datetime.py
nti/externalization/dublincore.py
nti/externalization/extension_points.py
nti/externalization/factory.py
nti/externalization/integer_strings.py
nti/externalization/interfaces.py
nti/externalization/meta.zcml
nti/externalization/numbers.py
nti/externalization/oids.py
nti/externalization/persistence.py
nti/externalization/proxy.py
nti/externalization/representation.py
nti/externalization/singleton.c
nti/externalization/singleton.py
nti/externalization/testing.py
nti/externalization/zcml.py
nti/externalization/externalization/__init__.py
nti/externalization/externalization/_decorate.cpython-313t-x86_64-linux-gnu.so
nti/externalization/externalization/_decorate.pxd
nti/externalization/externalization/_dictionary.cpython-313t-x86_64-linux-gnu.so
nti/externalization/externalization/_dictionary.pxd
nti/externalization/externalization/_externalizer.cpython-313t-x86_64-linux-gnu.so
nti/externalization/externalization/_externalizer.pxd
nti/externalization/externalization/_fields.cpython-313t-x86_64-linux-gnu.so
nti/externalization/externalization/_fields.pxd
nti_externalization-2.5.0.dist-info/METADATA
nti_externalization-2.5.0.dist-info/WHEEL
nti_externalization-2.5.0.dist-info/entry_points.txt
nti_externalization-2.5.0.dist-info/top_level.txt
nti_externalization-2.5.0.dist-info/zip-safe
nti_externalization-2.5.0.dist-info/RECORD
nti_externalization-2.5.0.dist-info/licenses/AUTHORS
nti_externalization-2.5.0.dist-info/licenses/LICENSE
