Metadata-Version: 2.4
Name: nti.externalization
Version: 2.5.0
Summary: NTI Externalization
Home-page: https://github.com/OpenNTI/nti.externalization
Author: Jason Madden
Author-email: jason@nextthought.com
License: Apache-2.0
Keywords: externalization
Classifier: Intended Audience :: Developers
Classifier: Natural Language :: English
Classifier: Operating System :: OS Independent
Classifier: Programming Language :: Python :: 3
Classifier: Programming Language :: Python :: 3 :: Only
Classifier: Programming Language :: Python :: 3.10
Classifier: Programming Language :: Python :: 3.11
Classifier: Programming Language :: Python :: 3.12
Classifier: Programming Language :: Python :: 3.13
Classifier: Programming Language :: Python :: 3.14
Classifier: Programming Language :: Python :: Implementation :: CPython
Classifier: Programming Language :: Python :: Implementation :: PyPy
Requires-Python: >=3.10
License-File: LICENSE
License-File: AUTHORS
Requires-Dist: nti.schema>=1.17.0
Requires-Dist: PyYAML>=5.1
Requires-Dist: isodate
Requires-Dist: pytz
Requires-Dist: simplejson>=3.19
Requires-Dist: transaction
Requires-Dist: zope.component>=4.6.1
Requires-Dist: zope.configuration>=4.4.0
Requires-Dist: zope.dottedname>=4.3.0
Requires-Dist: zope.event>=4.4.0
Requires-Dist: zope.hookable>=5.0.1
Requires-Dist: zope.interface>=5.0.1
Requires-Dist: zope.lifecycleevent>=4.3.0
Requires-Dist: zope.location>=4.2.0
Requires-Dist: zope.mimetype>=2.5.0
Requires-Dist: zope.proxy>=4.3.5
Requires-Dist: zope.schema>=6.0.0
Requires-Dist: zope.security>=5.1.1
Provides-Extra: zodb
Requires-Dist: ZODB>=5.5.1; extra == "zodb"
Requires-Dist: persistent>=4.7.0; extra == "zodb"
Requires-Dist: zope.container>=4.4.0; extra == "zodb"
Requires-Dist: zope.dublincore>=4.2.0; extra == "zodb"
Requires-Dist: zope.intid>=4.3.0; extra == "zodb"
Requires-Dist: BTrees>=4.8.0; extra == "zodb"
Provides-Extra: test
Requires-Dist: nti.testing>=4.4.0; extra == "test"
Requires-Dist: zope.testrunner; extra == "test"
Requires-Dist: manuel; extra == "test"
Requires-Dist: pyperf; extra == "test"
Requires-Dist: transaction>=5.0; extra == "test"
Provides-Extra: docs
Requires-Dist: Sphinx; extra == "docs"
Requires-Dist: repoze.sphinx.autointerface; extra == "docs"
Requires-Dist: sphinx_rtd_theme; extra == "docs"
Provides-Extra: benchmarks
Requires-Dist: pyperf; extra == "benchmarks"
Dynamic: author
Dynamic: author-email
Dynamic: classifier
Dynamic: description
Dynamic: home-page
Dynamic: keywords
Dynamic: license
Dynamic: license-file
Dynamic: provides-extra
Dynamic: requires-dist
Dynamic: requires-python
Dynamic: summary
